visadore/__init__.py
visadore/base.py
visadore/identity.py
visadore/instrument.py
visadore/mock_instrument/__init__.py
visadore/mock_instrument/feature.py
visadore/test/__init__.py
visadore/test/test_identity_parser.py
visadore/test/test_mock_instrument.py
visadore-1.0.dist-info/LICENSE.txt
visadore-1.0.dist-info/METADATA
visadore-1.0.dist-info/WHEEL
visadore-1.0.dist-info/entry_points.txt
visadore-1.0.dist-info/top_level.txt
visadore-1.0.dist-info/RECORD
