Metadata-Version: 2.1
Name: visadore
Version: 1.0
Summary: A plugin manager for modules that implement complex pyvisa resource interactions
Home-page: https://github.com/cwstryker/visadore
Author: Chadwick Stryker
Author-email: "cwsaccts@stryker5.org"
License: UNKNOWN
Platform: UNKNOWN
Classifier: Development Status :: 4 - Beta
Classifier: License :: OSI Approved :: Apache Software License
Classifier: Programming Language :: Python
Classifier: Programming Language :: Python :: 3
Classifier: Programming Language :: Python :: 3.5
Classifier: Programming Language :: Python :: 3.6
Classifier: Programming Language :: Python :: 3.7
Classifier: Programming Language :: Python :: 3.8
Classifier: Intended Audience :: Developers
Classifier: Environment :: Console
Requires-Python: >=3.5
Requires-Dist: pyvisa
Requires-Dist: stevedore
